[
  {
    "id": "1001",
    "company id": 1,
    "message": "welcome Hotel California!",
    "variables": ["guest", "company"]
  },
  {
    "id": "1002",
    "company id": 2,
    "message": "welcome The Grand Budapest Hotel!",
    "variables": ["guest", "company", "resort"]
  },
  {
    "id": "1003",
    "company id": 3,
    "message": "welcome The Heartbreak Hotel!",
    "variables": ["guest", "company"]
  },
  {
    "id": "1005",
    "company id": 4,
    "message": "welcome The Prancing Pony!",
    "variables": ["guest", "company"]
  },
  {
    "id": "1006",
    "company id": 5,
    "message": "welcome The Fawlty Towers!",
    "variables": ["guest", "company"]
  },
  {
    "id": "1007",
    "company id": 5,
    "message": "Happy Holidays!",
    "variables": ["guest", "company", "holiday"]
  }
]
